pytest_bdd/__init__.py
pytest_bdd/compat.py
pytest_bdd/cucumber_json.py
pytest_bdd/exceptions.py
pytest_bdd/feature.py
pytest_bdd/generation.py
pytest_bdd/gherkin_parser.py
pytest_bdd/gherkin_terminal_reporter.py
pytest_bdd/hooks.py
pytest_bdd/parser.py
pytest_bdd/parsers.py
pytest_bdd/plugin.py
pytest_bdd/py.typed
pytest_bdd/reporting.py
pytest_bdd/scenario.py
pytest_bdd/scripts.py
pytest_bdd/steps.py
pytest_bdd/templates/test.py.mak
pytest_bdd/types.py
pytest_bdd/utils.py
pytest_bdd-8.0.0.dist-info/AUTHORS.rst
pytest_bdd-8.0.0.dist-info/LICENSE.txt
pytest_bdd-8.0.0.dist-info/METADATA
pytest_bdd-8.0.0.dist-info/WHEEL
pytest_bdd-8.0.0.dist-info/entry_points.txt
pytest_bdd-8.0.0.dist-info/RECORD
