Metadata-Version: 2.1
Name: pytest-bdd
Version: 8.0.0
Summary: BDD for pytest
Home-page: https://pytest-bdd.readthedocs.io/
License: MIT
Author: Oleg Pidsadnyi
Author-email: oleg.pidsadnyi@gmail.com
Maintainer: Alessio Bogon
Maintainer-email: 778703+youtux@users.noreply.github.com
Requires-Python: >=3.9
Classifier: Development Status :: 6 - Mature
Classifier: Intended Audience :: Developers
Classifier: License :: OSI Approved :: MIT License
Classifier: Operating System :: MacOS :: MacOS X
Classifier: Operating System :: Microsoft :: Windows
Classifier: Operating System :: POSIX
Classifier: Programming Language :: Python :: 3
Classifier: Programming Language :: Python :: 3.9
Classifier: Programming Language :: Python :: 3.10
Classifier: Programming Language :: Python :: 3.11
Classifier: Programming Language :: Python :: 3.12
Classifier: Programming Language :: Python :: 3.13
Classifier: Topic :: Software Development :: Libraries
Classifier: Topic :: Software Development :: Testing
Classifier: Topic :: Utilities
Requires-Dist: Mako
Requires-Dist: gherkin-official (>=29.0.0,<30.0.0)
Requires-Dist: packaging
Requires-Dist: parse
Requires-Dist: parse-type
Requires-Dist: pytest (>=7.0.0)
Requires-Dist: typing-extensions
Project-URL: Documentation, https://pytest-bdd.readthedocs.io/
Project-URL: Repository, https://github.com/pytest-dev/pytest-bdd
